types_remover/__init__.py
types_remover/_types_remover_ast.py
types_remover/_types_remover_if.py
types_remover-1.0.0.dist-info/METADATA
types_remover-1.0.0.dist-info/WHEEL
types_remover-1.0.0.dist-info/licenses/LICENSE
types_remover-1.0.0.dist-info/RECORD
