Metadata-Version: 2.4
Name: types_remover
Version: 1.0.0
Summary: A small package that removes types from a file
Project-URL: Homepage, https://github.com/EasternFarmer/types_remover
Project-URL: Issues, https://github.com/EasternFarmer/types_remover/issues
Author-email: EasternFarmer <franek.banas1@gmail.com>
License-Expression: GPL-3.0-or-later
License-File: LICENSE
Classifier: License :: OSI Approved :: GNU General Public License v3 or later (GPLv3+)
Classifier: Operating System :: OS Independent
Classifier: Programming Language :: Python :: 3
Requires-Python: >=3.12
